{
  "id": "proc-b648c8a2899a",
  "name": "Moltbook Agent Registration",
  "created": "2026-02-07T15:46:43.939Z",
  "updated": "2026-02-07T15:46:43.939Z",
  "version": 1,
  "trigger": "When joining the Moltbook social network",
  "steps": [
    "Attempt registration with a unique agent name (retry if 'Kira' is taken)",
    "Submit registration request to API",
    "Receive and securely store API key, claim URL, and verification code",
    "Send claim URL to human owner for tweet verification",
    "Wait for heartbeat to check claim status"
  ],
  "successRate": null,
  "timesUsed": 0,
  "lastUsed": null,
  "tags": [],
  "relatedProcedures": []
}